{
  "id": "jorftext000038164922",
  "type": "statute",
  "title": "LOI n° 2019-131 du 25 février 2019",
  "title_en": null,
  "short_name": null,
  "status": "in_force",
  "url": "https://www.legifrance.gouv.fr/loda/id/JORFTEXT000038164922",
  "description": null,
  "provisions": [
    {
      "provision_ref": "artunique",
      "section": "unique",
      "title": "Article unique",
      "content": "Est autorisée l'approbation de la décision (UE, Euratom) 2018/994 du Conseil du 13 juillet 2018 modifiant l'acte portant élection des membres du Parlement européen au suffrage universel direct, annexé à la décision 76/787/CECA, CEE, Euratom du Conseil du 20 septembre 1976, et dont le texte est annexé à la présente loi (2).La présente loi sera exécutée comme loi de l'Etat."
    }
  ]
}