{
  "id": "loi-n-96-1107-du-18-decembre-1996",
  "type": "statute",
  "title": "Loi n° 96-1107 du 18 décembre 1996",
  "title_en": null,
  "short_name": null,
  "status": "in_force",
  "url": "https://www.legifrance.gouv.fr/loda/id/JORFTEXT000000196731",
  "description": null,
  "provisions": [
    {
      "provision_ref": "art2",
      "section": "2",
      "title": "Article 2",
      "content": "La présente loi est applicable dans les territoires d'outre-mer et à Mayotte."
    },
    {
      "provision_ref": "art3",
      "section": "3",
      "title": "Article 3",
      "content": "La présente loi entre en vigueur au terme d'un délai de six mois à compter de sa promulgation.\n\nElle n'est pas applicable aux actes authentiques constatant dans les six mois à compter de la date d'entrée en vigueur de la présente loi une vente réalisée antérieurement à cette entrée en vigueur ou intervenant à la suite d'une promesse unilatérale de vente ou d'achat dont la date est antérieure à cette entrée en vigueur, ni aux décisions judiciaires constatant une vente réalisée antérieurement à cette entrée en vigueur."
    }
  ]
}